pymiwifi/__init__.py
pymiwifi/api.py
pymiwifi-0.0.2.dist-info/METADATA
pymiwifi-0.0.2.dist-info/RECORD
pymiwifi-0.0.2.dist-info/WHEEL
pymiwifi-0.0.2.dist-info/top_level.txt
