Metadata-Version: 2.1
Name: pymiwifi
Version: 0.0.2
Summary: A python API to the Xiaomi Mi WiFi Router web interface
Home-page: https://github.com/pycampers/pymiwifi
Author: Dev Aggarwal
Author-email: devxpy@gmail.com
License: MIT
Platform: UNKNOWN
Classifier: License :: OSI Approved :: MIT License
Classifier: Programming Language :: Python
Classifier: Programming Language :: Python :: 3
Classifier: Programming Language :: Python :: 3.6
Classifier: Programming Language :: Python :: Implementation :: CPython
Classifier: Programming Language :: Python :: Implementation :: PyPy
Requires-Python: >=3.6.0
Requires-Dist: requests
